focalize/__init__.py
focalize/main.py
focalize/py.typed
focalize-0.1.0.dist-info/LICENSE.md
focalize-0.1.0.dist-info/METADATA
focalize-0.1.0.dist-info/WHEEL
focalize-0.1.0.dist-info/entry_points.txt
focalize-0.1.0.dist-info/RECORD
