Metadata-Version: 2.1
Name: focalize
Version: 0.1.0
Summary: Provide a formatter for loguru loggers that indents and contextualizes log blocks
License: MIT
Author: Tucker Beck
Author-email: tucker.beck@gmail.com
Requires-Python: >=3.8
Classifier: License :: OSI Approved :: MIT License
Classifier: Programming Language :: Python :: 3
Classifier: Programming Language :: Python :: 3.8
Classifier: Programming Language :: Python :: 3.9
Classifier: Programming Language :: Python :: 3.10
Classifier: Programming Language :: Python :: 3.11
Requires-Dist: loguru (>=0.5)
Requires-Dist: pendulum (>=2.0)
